README.md
setup.py
async_dali/__init__.py
async_dali/address.py
async_dali/bus_transciever.py
async_dali/dali_alliance_db.py
async_dali/gear.py
async_dali/gear_state_monitor.py
async_dali/test_address.py
async_dali/tridonic.py
async_dali/types.py
async_dali.egg-info/PKG-INFO
async_dali.egg-info/SOURCES.txt
async_dali.egg-info/dependency_links.txt
async_dali.egg-info/requires.txt
async_dali.egg-info/top_level.txt