Metadata-Version: 2.1
Name: async-dali
Version: 0.1.7
Summary: A module to discover devices and send commands to DALI enabled lights
Home-page: https://github.com/brucejcooper/py_async_dali
Author: Bruce Cooper
License: MIT
Platform: UNKNOWN
